{
    "Fal'Cie": {
        "Level": "7",
        "Race": "Wood Elf",
        "classes/levels": [
            [
                "Wildfire",
                "Druid",
                "6"
            ],
            [
                "Draconic",
                "Bloodline",
                "Sorcerer",
                "1"
            ]
        ],
        "HP": "66",
        "AC": "18",
        "Init": "+5",
        "Speed": "35 ft",
        "Languages": [
            "Common",
            "Elvish",
            "Druidic",
            "Draconic"
        ],
        "Stats": {
            "STR": {
                "Total": "11",
                "Modifier": "+0"
            },
            "DEX": {
                "Total": "20",
                "Modifier": "+5"
            },
            "CON": {
                "Total": "18",
                "Modifier": "+4"
            },
            "INT": {
                "Total": "13",
                "Modifier": "+1"
            },
            "WIS": {
                "Total": "20",
                "Modifier": "+5"
            },
            "CHA": {
                "Total": "13",
                "Modifier": "+1"
            }
        },
        "Saving Throws": {
            "Strength": {
                "Prof": "Not Proficient",
                "Mod": "+0"
            },
            "Dexterity": {
                "Prof": "Not Proficient",
                "Mod": "+5"
            },
            "Constitution": {
                "Prof": "Not Proficient",
                "Mod": "+4"
            },
            "Intelligence": {
                "Prof": "Proficient",
                "Mod": "+4"
            },
            "Wisdom": {
                "Prof": "Proficient",
                "Mod": "+8"
            },
            "Charisma": {
                "Prof": "Not Proficient",
                "Mod": "+1"
            }
        },
        "Skills": {
            "Acrobatics": {
                "Prof": "Not Proficient",
                "Mod": "+5"
            },
            "Animal Handling": {
                "Prof": "Not Proficient",
                "Mod": "+5"
            },
            "Arcana": {
                "Prof": "Proficient",
                "Mod": "+4"
            },
            "Athletics": {
                "Prof": "Not Proficient",
                "Mod": "+0"
            },
            "Deception": {
                "Prof": "Not Proficient",
                "Mod": "+1"
            },
            "History": {
                "Prof": "Not Proficient",
                "Mod": "+1"
            },
            "Insight": {
                "Prof": "Not Proficient",
                "Mod": "+5"
            },
            "Intimidation": {
                "Prof": "Not Proficient",
                "Mod": "+1"
            },
            "Investigation": {
                "Prof": "Not Proficient",
                "Mod": "+1"
            },
            "Medicine": {
                "Prof": "Proficient",
                "Mod": "+8"
            },
            "Nature": {
                "Prof": "Not Proficient",
                "Mod": "+1"
            },
            "Perception": {
                "Prof": "Proficient",
                "Mod": "+8"
            },
            "Performance": {
                "Prof": "Not Proficient",
                "Mod": "+1"
            },
            "Persuasion": {
                "Prof": "Not Proficient",
                "Mod": "+1"
            },
            "Religion": {
                "Prof": "Proficient",
                "Mod": "+4"
            },
            "Sleight of Hand": {
                "Prof": "Not Proficient",
                "Mod": "+5"
            },
            "Stealth": {
                "Prof": "Not Proficient",
                "Mod": "+5"
            }
        },
        "Casting": {
            "Details": {
                "Class": "",
                "Save DC": "Wisdom",
                "Ability": "16",
                "Attack Bonus": "+8",
                "Spells": {
                    "0": [
                        "Primal Savagery",
                        "Lightning Lure",
                        "Shillelagh",
                        "Mind Sliver",
                        "Gust",
                        "Guidance",
                        "Dancing Lights",
                        "Shape Water"
                    ],
                    "1": [
                        "Burning Hands",
                        "Beast Bond",
                        "Shield",
                        "Cure Wounds",
                        "Goodberry",
                        "Sleep",
                        "Absorb Elements",
                        "Ice Knife",
                        "Magic Missile",
                        "Healing Word",
                        "Faerie Fire"
                    ],
                    "2": [
                        "Flaming Sphere",
                        "Protection from Poison",
                        "Scorching Ray",
                        "Wither and Bloom",
                        "Moonbeam",
                        "Healing Spirit"
                    ],
                    "3": [
                        "Revivify",
                        "Plant Growth",
                        "Call Lightning",
                        "Protection from Energy"
                    ],
                    "4": [],
                    "5": [],
                    "6": [],
                    "7": [],
                    "8": [],
                    "9": []
                }
            }
        },
        "Description": {
            "AGE": "121",
            "GENDER": "Male",
            "HEIGHT": "6'3",
            "EYES": "Amber",
            "WEIGHT": "145 lb.",
            "HAIR": "Blond",
            "SIZE": "Medium",
            "SKIN": "Fair",
            "IMAGE": "https://i.pinimg.com/736x/0c/5d/71/0c5d71429695bc179b6d9de51d98f844.jpg"
        }
    }
}